[{"id":1790864,"leechers":"30493","peers":"117596","seeders":"87103"},{"id":2015381,"leechers":"8441","peers":"58988","seeders":"50548"},{"id":2872718,"leechers":"20364","peers":"50523","seeders":"30159"},{"id":1291150,"leechers":"8472","peers":"41645","seeders":"33173"},{"id":2713180,"leechers":"7842","peers":"41310","seeders":"33467"},{"id":2103281,"leechers":"6212","peers":"35547","seeders":"29335"},{"id":2397535,"leechers":"5376","peers":"32863","seeders":"27488"},{"id":2872732,"leechers":"7474","peers":"32235","seeders":"24761"},{"id":829150,"leechers":"6872","peers":"27441","seeders":"20569"},{"id":1772264,"leechers":"8379","peers":"25714","seeders":"17335"}]