[{"id":1790864,"leechers":"29819","peers":"114270","seeders":"84451"},{"id":2015381,"leechers":"9477","peers":"60630","seeders":"51154"},{"id":2872718,"leechers":"17829","peers":"49176","seeders":"31347"},{"id":1291150,"leechers":"8518","peers":"40637","seeders":"32119"},{"id":2713180,"leechers":"7661","peers":"40171","seeders":"32511"},{"id":2103281,"leechers":"6684","peers":"36222","seeders":"29538"},{"id":2397535,"leechers":"5399","peers":"31954","seeders":"26555"},{"id":2872732,"leechers":"7516","peers":"31906","seeders":"24390"},{"id":829150,"leechers":"6518","peers":"26788","seeders":"20270"},{"id":1772264,"leechers":"7262","peers":"24638","seeders":"17375"}]