[{"delta":"535","id":1790864,"imdb_rating":73,"imdb_votes":63697,"leechers":"29660","peers":"114983","released":"2014-09-19T00:00:00Z","scrape":96,"seeders":"85323","title":"The Maze Runner","tomato_meter":63,"tomato_reviews":142,"tomato_user_meter":74,"tomato_user_reviews":63942,"trailer":"https://www.youtube.com/embed/K1In45K0DGc","yesterday":"114448"},{"delta":"3910","id":2015381,"imdb_rating":84,"imdb_votes":275806,"leechers":"10801","peers":"65076","released":"2014-08-01T00:00:00Z","scrape":97,"seeders":"54275","title":"Guardians of the Galaxy","tomato_meter":90,"tomato_reviews":250,"tomato_user_meter":94,"tomato_user_reviews":213337,"trailer":null,"yesterday":"61167"},{"delta":"-852","id":2872718,"imdb_rating":83,"imdb_votes":14849,"leechers":"15900","peers":"48350","released":"2014-10-31T00:00:00Z","scrape":96,"seeders":"32450","title":"Nightcrawler","tomato_meter":95,"tomato_reviews":186,"tomato_user_meter":87,"tomato_user_reviews":44842,"trailer":"https://www.youtube.com/embed/aLlNXTvoZ2o","yesterday":"49202"},{"delta":"1857","id":2713180,"imdb_rating":80,"imdb_votes":57395,"leechers":"8346","peers":"42087","released":"2014-10-17T00:00:00Z","scrape":96,"seeders":"33741","title":"Fury","tomato_meter":78,"tomato_reviews":206,"tomato_user_meter":88,"tomato_user_reviews":75482,"trailer":"https://www.youtube.com/embed/rren-FA3z8U","yesterday":"40231"},{"delta":"961","id":1291150,"imdb_rating":61,"imdb_votes":82317,"leechers":"8869","peers":"41469","released":"2014-08-08T00:00:00Z","scrape":96,"seeders":"32600","title":"Teenage Mutant Ninja Turtles","tomato_meter":22,"tomato_reviews":134,"tomato_user_meter":56,"tomato_user_reviews":117603,"trailer":"https://www.youtube.com/embed/VZZ0PnDZdZk","yesterday":"40509"},{"delta":"30006","id":1371150,"imdb_rating":67,"imdb_votes":7427,"leechers":"16762","peers":"41416","released":"2014-09-19T00:00:00Z","scrape":97,"seeders":"24654","title":"This Is Where I Leave You","tomato_meter":42,"tomato_reviews":140,"tomato_user_meter":66,"tomato_user_reviews":25542,"trailer":"https://www.youtube.com/embed/lS0cztRMuNY","yesterday":"11410"},{"delta":"2279","id":2103281,"imdb_rating":79,"imdb_votes":166096,"leechers":"7550","peers":"38705","released":"2014-07-11T00:00:00Z","scrape":97,"seeders":"31155","title":"Dawn of the Planet of the Apes","tomato_meter":91,"tomato_reviews":243,"tomato_user_meter":90,"tomato_user_reviews":187705,"trailer":"https://www.youtube.com/embed/t5ZGnsLVALk","yesterday":"36426"},{"delta":"1320","id":2872732,"imdb_rating":65,"imdb_votes":114266,"leechers":"7861","peers":"33419","released":"2014-07-25T00:00:00Z","scrape":96,"seeders":"25557","title":"Lucy","tomato_meter":66,"tomato_reviews":194,"tomato_user_meter":48,"tomato_user_reviews":112294,"trailer":"https://www.youtube.com/embed/osFJQJRXbKE","yesterday":"32099"},{"delta":"-534","id":2397535,"imdb_rating":75,"imdb_votes":29768,"leechers":"5404","peers":"31446","released":"2015-01-09T00:00:00Z","scrape":96,"seeders":"26042","title":"Predestination","tomato_meter":82,"tomato_reviews":22,"tomato_user_meter":95,"tomato_user_reviews":2150,"trailer":"https://www.youtube.com/embed/jcQacCfi_pw","yesterday":"31980"},{"delta":"-1073","id":829150,"imdb_rating":63,"imdb_votes":51683,"leechers":"6135","peers":"25730","released":"2014-10-10T00:00:00Z","scrape":98,"seeders":"19596","title":"Dracula Untold","tomato_meter":23,"tomato_reviews":108,"tomato_user_meter":61,"tomato_user_reviews":37668,"trailer":"https://www.youtube.com/embed/MJyvB0Q0-WA","yesterday":"26803"}]